yors_pano_argv_parse/__init__.py
yors_pano_argv_parse/main.py
yors_pano_argv_parse-0.1.0.dist-info/METADATA
yors_pano_argv_parse-0.1.0.dist-info/WHEEL
yors_pano_argv_parse-0.1.0.dist-info/RECORD
